nestipy_ioc/__init__.py
nestipy_ioc/annotation.py
nestipy_ioc/container.py
nestipy_ioc/context_container.py
nestipy_ioc/dependency.py
nestipy_ioc/meta.py
nestipy_ioc/middleware.py
nestipy_ioc/provider.py
nestipy_ioc/utils.py
nestipy_ioc-0.1.31.dist-info/METADATA
nestipy_ioc-0.1.31.dist-info/WHEEL
nestipy_ioc-0.1.31.dist-info/RECORD
