Metadata-Version: 2.1
Name: nestipy-ioc
Version: 0.1.31
Summary: 
Author: tsiresymila
Author-email: tsiresymila@gmail.com
Requires-Python: >=3.10,<4.0
Classifier: Programming Language :: Python :: 3
Classifier: Programming Language :: Python :: 3.10
Classifier: Programming Language :: Python :: 3.11
Classifier: Programming Language :: Python :: 3.12
Requires-Dist: nestipy-metadata (==0.1.1)
Requires-Dist: pydantic (>=2.7.0,<3.0.0)
